dataknobs_fsm/__init__.py
dataknobs_fsm/observability.py
dataknobs_fsm/py.typed
dataknobs_fsm/api/__init__.py
dataknobs_fsm/api/advanced.py
dataknobs_fsm/api/async_simple.py
dataknobs_fsm/api/simple.py
dataknobs_fsm/cli/__init__.py
dataknobs_fsm/cli/commands.py
dataknobs_fsm/cli/main.py
dataknobs_fsm/config/__init__.py
dataknobs_fsm/config/builder.py
dataknobs_fsm/config/loader.py
dataknobs_fsm/config/schema.py
dataknobs_fsm/config/validator.py
dataknobs_fsm/core/__init__.py
dataknobs_fsm/core/arc.py
dataknobs_fsm/core/context_factory.py
dataknobs_fsm/core/data_modes.py
dataknobs_fsm/core/data_wrapper.py
dataknobs_fsm/core/exceptions.py
dataknobs_fsm/core/fsm.py
dataknobs_fsm/core/modes.py
dataknobs_fsm/core/network.py
dataknobs_fsm/core/result_formatter.py
dataknobs_fsm/core/state.py
dataknobs_fsm/core/transactions.py
dataknobs_fsm/execution/__init__.py
dataknobs_fsm/execution/async_batch.py
dataknobs_fsm/execution/async_engine.py
dataknobs_fsm/execution/async_stream.py
dataknobs_fsm/execution/base_engine.py
dataknobs_fsm/execution/batch.py
dataknobs_fsm/execution/common.py
dataknobs_fsm/execution/context.py
dataknobs_fsm/execution/engine.py
dataknobs_fsm/execution/history.py
dataknobs_fsm/execution/network.py
dataknobs_fsm/execution/stream.py
dataknobs_fsm/functions/__init__.py
dataknobs_fsm/functions/base.py
dataknobs_fsm/functions/manager.py
dataknobs_fsm/functions/library/__init__.py
dataknobs_fsm/functions/library/database.py
dataknobs_fsm/functions/library/streaming.py
dataknobs_fsm/functions/library/transformers.py
dataknobs_fsm/functions/library/validators.py
dataknobs_fsm/io/__init__.py
dataknobs_fsm/io/adapters.py
dataknobs_fsm/io/base.py
dataknobs_fsm/io/utils.py
dataknobs_fsm/patterns/__init__.py
dataknobs_fsm/patterns/api_orchestration.py
dataknobs_fsm/patterns/error_recovery.py
dataknobs_fsm/patterns/etl.py
dataknobs_fsm/patterns/file_processing.py
dataknobs_fsm/resources/__init__.py
dataknobs_fsm/resources/base.py
dataknobs_fsm/resources/database.py
dataknobs_fsm-0.1.6.dist-info/METADATA
dataknobs_fsm-0.1.6.dist-info/WHEEL
dataknobs_fsm-0.1.6.dist-info/entry_points.txt
dataknobs_fsm-0.1.6.dist-info/RECORD
